shortener/__init__.py
shortener/__main__.py
urlzap-2.0.1.dist-info/METADATA
urlzap-2.0.1.dist-info/WHEEL
urlzap-2.0.1.dist-info/entry_points.txt
urlzap-2.0.1.dist-info/top_level.txt
urlzap-2.0.1.dist-info/RECORD
