Metadata-Version: 2.4
Name: urlzap
Version: 2.0.1
Summary: A CLI tool to shorten URLs from your terminal.
Home-page: https://github.com/yadavkapil23/url-shortener-cli
Author: Kapil
Classifier: Programming Language :: Python :: 3
Classifier: License :: OSI Approved :: MIT License
Classifier: Operating System :: OS Independent
Classifier: Environment :: Console
Classifier: Intended Audience :: Developers
Classifier: Topic :: Utilities
Requires-Python: >=3.7
Requires-Dist: requests
Dynamic: author
Dynamic: classifier
Dynamic: description
Dynamic: description-content-type
Dynamic: home-page
Dynamic: requires-dist
Dynamic: requires-python
Dynamic: summary
